textgrid_tools/__init__.py
textgrid_tools/cloning.py
textgrid_tools/comparison.py
textgrid_tools/globals.py
textgrid_tools/helper.py
textgrid_tools/validation.py
textgrid_tools/grid/__init__.py
textgrid_tools/grid/audio_synchronization.py
textgrid_tools/grid/creation.py
textgrid_tools/grid/splitting.py
textgrid_tools/grid/stats_generation.py
textgrid_tools/grids/__init__.py
textgrid_tools/grids/dictionary_exporting.py
textgrid_tools/grids/durations_labelling.py
textgrid_tools/grids/durations_plotting.py
textgrid_tools/grids/grid_merging.py
textgrid_tools/grids/marks_exporting.py
textgrid_tools/grids/stats_generation.py
textgrid_tools/intervals/__init__.py
textgrid_tools/intervals/between_marks_joining.py
textgrid_tools/intervals/between_pause_joining.py
textgrid_tools/intervals/boundary_fixing.py
textgrid_tools/intervals/boundary_joining.py
textgrid_tools/intervals/common.py
textgrid_tools/intervals/duration_joining.py
textgrid_tools/intervals/durations_plotting.py
textgrid_tools/intervals/joining.py
textgrid_tools/intervals/mark_joining.py
textgrid_tools/intervals/removing.py
textgrid_tools/intervals/splitting.py
textgrid_tools/intervals/symbols_joining.py
textgrid_tools/intervals/template_joining.py
textgrid_tools/intervals/text_replacement.py
textgrid_tools/tier/__init__.py
textgrid_tools/tier/cloning.py
textgrid_tools/tier/exporting.py
textgrid_tools/tier/importing.py
textgrid_tools/tier/mapping.py
textgrid_tools/tier/moving.py
textgrid_tools/tier/renaming.py
textgrid_tools/tiers/__init__.py
textgrid_tools/tiers/marks_mapping.py
textgrid_tools/tiers/removing.py
textgrid_tools/tiers/silence_labeling.py
textgrid_tools/tiers/symbol_removing.py
textgrid_tools/tiers/transcription.py
textgrid_tools_cli/__init__.py
textgrid_tools_cli/cli.py
textgrid_tools_cli/common.py
textgrid_tools_cli/globals.py
textgrid_tools_cli/helper.py
textgrid_tools_cli/logging_configuration.py
textgrid_tools_cli/textgrid_io.py
textgrid_tools_cli/validation.py
textgrid_tools-0.0.8.dist-info/LICENSE
textgrid_tools-0.0.8.dist-info/METADATA
textgrid_tools-0.0.8.dist-info/WHEEL
textgrid_tools-0.0.8.dist-info/entry_points.txt
textgrid_tools-0.0.8.dist-info/top_level.txt
textgrid_tools-0.0.8.dist-info/RECORD
