Metadata-Version: 2.1
Name: textgrid-tools
Version: 0.0.8
Summary: Command-line interface (CLI) to modify TextGrids and their corresponding audio files.
Author-email: Stefan Taubert <pypi@stefantaubert.com>
Maintainer-email: Stefan Taubert <pypi@stefantaubert.com>
License: MIT
Project-URL: Homepage, https://github.com/stefantaubert/textgrid-ipa
Project-URL: Issues, https://github.com/stefantaubert/textgrid-ipa/issues
Keywords: Text-to-speech,Speech synthesis,praat,TextGrid,Utils,Language,Linguistics
Classifier: Development Status :: 2 - Pre-Alpha
Classifier: Operating System :: OS Independent
Classifier: Operating System :: MacOS
Classifier: Operating System :: POSIX
Classifier: Operating System :: POSIX :: BSD
Classifier: Operating System :: POSIX :: Linux
Classifier: Operating System :: Unix
Classifier: Operating System :: Microsoft :: Windows
Classifier: Programming Language :: Python
Classifier: Programming Language :: Python :: 3
Classifier: Programming Language :: Python :: 3.8
Classifier: Programming Language :: Python :: 3.9
Classifier: Programming Language :: Python :: 3.10
Classifier: Programming Language :: Python :: 3.11
Classifier: License :: OSI Approved :: MIT License
Requires-Python: <4,>=3.8
License-File: LICENSE
Requires-Dist: numpy (>=1.18.5)
Requires-Dist: scipy (>=1.8.0)
Requires-Dist: tqdm (>=4.63.0)
Requires-Dist: TextGrid (>=1.5)
Requires-Dist: pandas (>=1.4.0)
Requires-Dist: ordered-set (>=4.1.0)
Requires-Dist: matplotlib (>=3.5.0)
Requires-Dist: pronunciation-dictionary (>=0.0.5)
